meross_iot/__init__.py
meross_iot/device_factory.py
meross_iot/error_budget.py
meross_iot/http_api.py
meross_iot/manager.py
meross_iot/controller/__init__.py
meross_iot/controller/device.py
meross_iot/controller/subdevice.py
meross_iot/controller/mixins/__init__.py
meross_iot/controller/mixins/alarm.py
meross_iot/controller/mixins/consumption.py
meross_iot/controller/mixins/diffuser_light.py
meross_iot/controller/mixins/diffuser_spray.py
meross_iot/controller/mixins/dnd.py
meross_iot/controller/mixins/electricity.py
meross_iot/controller/mixins/encryption.py
meross_iot/controller/mixins/garage.py
meross_iot/controller/mixins/hub.py
meross_iot/controller/mixins/light.py
meross_iot/controller/mixins/roller_shutter.py
meross_iot/controller/mixins/runtime.py
meross_iot/controller/mixins/spray.py
meross_iot/controller/mixins/system.py
meross_iot/controller/mixins/thermostat.py
meross_iot/controller/mixins/toggle.py
meross_iot/model/__init__.py
meross_iot/model/constants.py
meross_iot/model/credentials.py
meross_iot/model/enums.py
meross_iot/model/exception.py
meross_iot/model/shared.py
meross_iot/model/typing.py
meross_iot/model/http/__init__.py
meross_iot/model/http/device.py
meross_iot/model/http/error_codes.py
meross_iot/model/http/exception.py
meross_iot/model/http/subdevice.py
meross_iot/model/plugin/__init__.py
meross_iot/model/plugin/hub.py
meross_iot/model/plugin/light.py
meross_iot/model/plugin/power.py
meross_iot/model/push/__init__.py
meross_iot/model/push/alarm.py
meross_iot/model/push/bind.py
meross_iot/model/push/common.py
meross_iot/model/push/factory.py
meross_iot/model/push/generic.py
meross_iot/model/push/online.py
meross_iot/model/push/unbind.py
meross_iot/model/push/water_leak.py
meross_iot/utilities/__init__.py
meross_iot/utilities/conversion.py
meross_iot/utilities/misc.py
meross_iot/utilities/mqtt.py
meross_iot/utilities/network.py
meross_iot/utilities/stats.py
meross_iot-0.4.10.3.data/data/.version
meross_iot-0.4.10.3.dist-info/licenses/LICENSE
utilities/__init__.py
meross_iot-0.4.10.3.dist-info/METADATA
meross_iot-0.4.10.3.dist-info/WHEEL
meross_iot-0.4.10.3.dist-info/entry_points.txt
meross_iot-0.4.10.3.dist-info/top_level.txt
meross_iot-0.4.10.3.dist-info/RECORD
