Metadata-Version: 2.4
Name: meross_iot
Version: 0.4.10.3
Summary: A simple library to deal with Meross devices. At the moment MSS110, MSS210, MSS310, MSS310H smart plugs and the MSS425E power strip. Other meross device might work out of the box with limited functionality. Give it a try and, in case of problems, let the developer know by opening an issue on Github.
Home-page: https://github.com/albertogeniola/MerossIot
Author: Alberto Geniola
Author-email: albertogeniola@gmail.com
License: MIT
Project-URL: Documentation, https://github.com/albertogeniola/MerossIot
Project-URL: Funding, https://donate.pypi.org
Project-URL: Source, https://github.com/albertogeniola/MerossIot
Project-URL: Tracker, https://github.com/albertogeniola/MerossIot/issues
Keywords: meross smartplug smartbulb iot mqtt domotic switch MSL120 MSS110 MSS210 MSS310 MSS310h MSS425e MSS530H MSG100 MSH300 MS100 MSS710 MSXH0
Classifier: Intended Audience :: Developers
Classifier: Programming Language :: Python :: 3
Classifier: Operating System :: OS Independent
Requires-Python: >=3.8
License-File: LICENSE
Requires-Dist: paho-mqtt<3.0.0,>=2.1.0
Requires-Dist: requests<3.0.0,>=2.19.1
Requires-Dist: aiohttp[speedups]<4.0.0,>=3.7.4.post0
Requires-Dist: pycryptodomex>=3.20.0
Dynamic: author
Dynamic: author-email
Dynamic: classifier
Dynamic: description
Dynamic: description-content-type
Dynamic: home-page
Dynamic: keywords
Dynamic: license
Dynamic: license-file
Dynamic: project-url
Dynamic: requires-dist
Dynamic: requires-python
Dynamic: summary
